snizhana.py
minekraftweb-0.0.1.dist-info/LICENSE.txt
minekraftweb-0.0.1.dist-info/METADATA
minekraftweb-0.0.1.dist-info/WHEEL
minekraftweb-0.0.1.dist-info/top_level.txt
minekraftweb-0.0.1.dist-info/RECORD
